README.txt
bootstrap.py
buildout.cfg
setup.py
collective/__init__.py
collective.psc.mirroring.egg-info/PKG-INFO
collective.psc.mirroring.egg-info/SOURCES.txt
collective.psc.mirroring.egg-info/dependency_links.txt
collective.psc.mirroring.egg-info/entry_points.txt
collective.psc.mirroring.egg-info/namespace_packages.txt
collective.psc.mirroring.egg-info/not-zip-safe
collective.psc.mirroring.egg-info/requires.txt
collective.psc.mirroring.egg-info/top_level.txt
collective/psc/__init__.py
collective/psc/mirroring/__init__.py
collective/psc/mirroring/config.py
collective/psc/mirroring/configure.zcml
collective/psc/mirroring/interfaces.py
collective/psc/mirroring/locker.py
collective/psc/mirroring/profiles.zcml
collective/psc/mirroring/browser/__init__.py
collective/psc/mirroring/browser/config.py
collective/psc/mirroring/browser/configure.zcml
collective/psc/mirroring/profiles/default/componentregistry.xml
collective/psc/mirroring/profiles/default/controlpanel.xml
collective/psc/mirroring/profiles/default/metadata.xml
collective/psc/mirroring/subscribers/__init__.py
collective/psc/mirroring/subscribers/configure.zcml
collective/psc/mirroring/subscribers/modified.py
collective/psc/mirroring/tests/__init__.py
collective/psc/mirroring/tests/configure.zcml
collective/psc/mirroring/tests/sample.tar.gz
collective/psc/mirroring/tests/test_config.py
collective/psc/mirroring/tests/test_event.py
collective/psc/mirroring/tests/test_lock.py
docs/HISTORY.txt