Metadata-Version: 1.0
Name: collective.psc.mirroring
Version: 0.1.3
Summary: Event-based mirroring tool
Home-page: http://svn.plone.org/svn/collective/collective.psc.mirroring
Author: Tarek Ziade
Author-email: tarek@ziade.org
License: GPL
Keywords: psc disutils mirroring
Platform: UNKNOWN
Classifier: Programming Language :: Python
Classifier: Topic :: Software Development :: Libraries :: Python Modules
